pysolvemath/__init__.py
pysolvemath/control_flow.py
pysolvemath/initial_guess.py
pysolvemath/parsing.py
pysolvemath/solver.py
pysolvemath/stop_solve.py
pysolvemath-0.3.dist-info/LICENSE
pysolvemath-0.3.dist-info/METADATA
pysolvemath-0.3.dist-info/WHEEL
pysolvemath-0.3.dist-info/top_level.txt
pysolvemath-0.3.dist-info/RECORD
