Metadata-Version: 2.1
Name: pysolvemath
Version: 0.3
Summary: Numeric Solver.
Home-page: https://github.com/yx-z/pysolvemath
Author: David
Author-email: yx.z@hotmail.com
Project-URL: Bug Tracker, https://github.com/yx-z/pysolvemath/issues
Classifier: Programming Language :: Python :: 3
Classifier: License :: OSI Approved :: MIT License
Classifier: Operating System :: OS Independent
License-File: LICENSE
